{
    "id": "240522-071920-382394",
    "user": {
        "user_id": "240522-071920-382394",
        "sex-group": "male",
        "age-group": "25-34",
        "education-group": "Undergraduate Degree",
        "condition": "20ad"
    },
    "ranking": [
        "Head-Airbag-Twist",
        "Frontend-Luftklappe",
        "Gurt-Cabrio",
        "Tuerschliessbuegel",
        "Wasserablaufschlauch",
        "DSC_Massekabel"
    ],
    "time": [
        39.81367,
        13.55373,
        17.811486,
        14.481257,
        26.709381,
        15.671781,
        16.069751,
        11.700572,
        11.000807,
        14.051042,
        18.333362,
        10.327479,
        11.340736,
        17.246234,
        17.678917,
        10.924074,
        14.50297,
        17.553272,
        11.857617,
        10.153604
    ],
    "summary": [
        {
            "index_i": 0,
            "index_j": 0,
            "use_case": "Tuerschliessbuegel",
            "sub_dir": "OK",
            "file": "WBA11AP0XRCR47603_ldKwZowBsfk0sxt0U99Z",
            "pics_label": true,
            "ai_advice": true,
            "is_ok_user": true,
            "marks_user": [],
            "timestamps": [
                [
                    1716362442021,
                    true
                ]
            ]
        },
        {
            "index_i": 0,
            "index_j": 1,
            "use_case": "Wasserablaufschlauch",
            "sub_dir": "NOK",
            "file": "WBA63FJ06RCR76764_zhAGaI0Bsfk0sxt0_cWH",
            "pics_label": false,
            "ai_advice": false,
            "is_ok_user": false,
            "marks_user": [],
            "timestamps": [
                [
                    1716362444272,
                    false
                ]
            ]
        },
        {
            "index_i": 0,
            "index_j": 2,
            "use_case": "Head-Airbag-Twist",
            "sub_dir": "OK",
            "file": "WBA12AV04RFT30549_NSdfBY8BWicZSVJ7g76d",
            "pics_label": true,
            "ai_advice": true,
            "is_ok_user": true,
            "marks_user": [],
            "timestamps": [
                [
                    1716362447616,
                    true
                ]
            ]
        },
        {
            "index_i": 0,
            "index_j": 3,
            "use_case": "Massekabel",
            "sub_dir": "OK",
            "file": "WBA21BP00RCR90888_zS8eq40Bsfk0sxt0w-nc",
            "pics_label": true,
            "ai_advice": true,
            "is_ok_user": false,
            "marks_user": [],
            "timestamps": [
                [
                    1716362453108,
                    false
                ]
            ]
        },
        {
            "index_i": 0,
            "index_j": 4,
            "use_case": "Gurt-Cabrio",
            "sub_dir": "NOK",
            "file": "WBAFY41020CN79044_8i1lvogBNI7gxFWPcKuM",
            "pics_label": false,
            "ai_advice": false,
            "is_ok_user": true,
            "marks_user": [],
            "timestamps": [
                [
                    1716362451403,
                    true
                ]
            ]
        },
        {
            "index_i": 0,
            "index_j": 5,
            "use_case": "Frontend-Luftklappe",
            "sub_dir": "OK",
            "file": "WBA11AJ060CR93229_9E3oso0BMQo0ENBQlXCt",
            "pics_label": true,
            "ai_advice": true,
            "is_ok_user": true,
            "marks_user": [],
            "timestamps": [
                [
                    1716362448914,
                    true
                ]
            ]
        },
        {
            "index_i": 1,
            "index_j": 0,
            "use_case": "Massekabel",
            "sub_dir": "OK",
            "file": "WBA21BP02RCR95591_OVLbwo0BMQo0ENBQgwzt",
            "pics_label": true,
            "ai_advice": false,
            "is_ok_user": false,
            "marks_user": [],
            "timestamps": [
                [
                    1716362474006,
                    false
                ]
            ]
        },
        {
            "index_i": 1,
            "index_j": 1,
            "use_case": "Gurt-Cabrio",
            "sub_dir": "OK",
            "file": "WBSDZ01080CR56338_1-Ro_4wBsfk0sxt0Wd-D",
            "pics_label": true,
            "ai_advice": false,
            "is_ok_user": true,
            "marks_user": [],
            "timestamps": [
                [
                    1716362475923,
                    true
                ]
            ]
        },
        {
            "index_i": 1,
            "index_j": 2,
            "use_case": "Frontend-Luftklappe",
            "sub_dir": "NOK",
            "file": "WBA21BP00RCR60659_wu9BHI0Bsfk0sxt0OCyp",
            "pics_label": false,
            "ai_advice": false,
            "is_ok_user": false,
            "marks_user": [],
            "timestamps": [
                [
                    1716362477515,
                    false
                ]
            ]
        },
        {
            "index_i": 1,
            "index_j": 3,
            "use_case": "Tuerschliessbuegel",
            "sub_dir": "NOK",
            "file": "WBA11AP0XRCP28298_6f2zl4kBUwXShj1F-p9z",
            "pics_label": false,
            "ai_advice": false,
            "is_ok_user": false,
            "marks_user": [],
            "timestamps": [
                [
                    1716362481285,
                    false
                ]
            ]
        },
        {
            "index_i": 1,
            "index_j": 4,
            "use_case": "Wasserablaufschlauch",
            "sub_dir": "NOK",
            "file": "WBA53FJ09RCR92694_ikiorI0BMQo0ENBQtJRb",
            "pics_label": false,
            "ai_advice": false,
            "is_ok_user": false,
            "marks_user": [],
            "timestamps": [
                [
                    1716362479881,
                    false
                ]
            ]
        },
        {
            "index_i": 1,
            "index_j": 5,
            "use_case": "Head-Airbag-Twist",
            "sub_dir": "OK",
            "file": "WBY71AW070FT31212_t-MZCY8Bsfk0sxt01QdG",
            "pics_label": true,
            "ai_advice": true,
            "is_ok_user": false,
            "marks_user": [],
            "timestamps": [
                [
                    1716362478897,
                    false
                ]
            ]
        },
        {
            "index_i": 2,
            "index_j": 0,
            "use_case": "Massekabel",
            "sub_dir": "NOK",
            "file": "WBA71BM020CP25175_o_vCkYkBUwXShj1FnJvl",
            "pics_label": false,
            "ai_advice": false,
            "is_ok_user": false,
            "marks_user": [],
            "timestamps": [
                [
                    1716362486891,
                    false
                ]
            ]
        },
        {
            "index_i": 2,
            "index_j": 1,
            "use_case": "Wasserablaufschlauch",
            "sub_dir": "OK",
            "file": "WBA43FJ02RCR91527_MDA9q40Bsfk0sxt04gif",
            "pics_label": true,
            "ai_advice": false,
            "is_ok_user": true,
            "marks_user": [],
            "timestamps": [
                [
                    1716362499084,
                    true
                ]
            ]
        },
        {
            "index_i": 2,
            "index_j": 2,
            "use_case": "Head-Airbag-Twist",
            "sub_dir": "NOK",
            "file": "WBA21AX040FT07909_yNSGVo4BWicZSVJ7_8-h",
            "pics_label": false,
            "ai_advice": false,
            "is_ok_user": false,
            "marks_user": [],
            "timestamps": [
                [
                    1716362497209,
                    false
                ]
            ]
        },
        {
            "index_i": 2,
            "index_j": 3,
            "use_case": "Gurt-Cabrio",
            "sub_dir": "NOK",
            "file": "WBSDZ0C02RCR44289_AxZgXowBWicZSVJ7sHeE",
            "pics_label": false,
            "ai_advice": false,
            "is_ok_user": true,
            "marks_user": [],
            "timestamps": [
                [
                    1716362489979,
                    true
                ]
            ]
        },
        {
            "index_i": 2,
            "index_j": 4,
            "use_case": "Tuerschliessbuegel",
            "sub_dir": "OK",
            "file": "WBA11AP0XRCR47620_choZZ4wBWicZSVJ7MEKK",
            "pics_label": true,
            "ai_advice": true,
            "is_ok_user": false,
            "marks_user": [],
            "timestamps": [
                [
                    1716362495069,
                    false
                ]
            ]
        },
        {
            "index_i": 2,
            "index_j": 5,
            "use_case": "Frontend-Luftklappe",
            "sub_dir": "NOK",
            "file": "WBA21BP01RCR89104_40RDp40BMQo0ENBQPJO1",
            "pics_label": false,
            "ai_advice": false,
            "is_ok_user": false,
            "marks_user": [],
            "timestamps": [
                [
                    1716362496427,
                    false
                ]
            ]
        },
        {
            "index_i": 3,
            "index_j": 0,
            "use_case": "Gurt-Cabrio",
            "sub_dir": "OK",
            "file": "WBADZ2C0XRCR79453_WxZ8eo0Bsfk0sxt0BM1m",
            "pics_label": true,
            "ai_advice": true,
            "is_ok_user": true,
            "marks_user": [],
            "timestamps": [
                [
                    1716362504867,
                    true
                ]
            ]
        },
        {
            "index_i": 3,
            "index_j": 1,
            "use_case": "Frontend-Luftklappe",
            "sub_dir": "OK",
            "file": "WBA21BP00RCR95542_dYEBwo0BWicZSVJ7Lksk",
            "pics_label": true,
            "ai_advice": true,
            "is_ok_user": false,
            "marks_user": [],
            "timestamps": [
                [
                    1716362510706,
                    false
                ]
            ]
        },
        {
            "index_i": 3,
            "index_j": 2,
            "use_case": "Wasserablaufschlauch",
            "sub_dir": "OK",
            "file": "WBA43FJ08RCR93962_XkzMsY0BMQo0ENBQSHlT",
            "pics_label": true,
            "ai_advice": false,
            "is_ok_user": true,
            "marks_user": [],
            "timestamps": [
                [
                    1716362512725,
                    true
                ]
            ]
        },
        {
            "index_i": 3,
            "index_j": 3,
            "use_case": "Massekabel",
            "sub_dir": "OK",
            "file": "WBA21BP0XRCR92535_FHvmsI0BWicZSVJ7Qazg",
            "pics_label": true,
            "ai_advice": true,
            "is_ok_user": true,
            "marks_user": [],
            "timestamps": [
                [
                    1716362505912,
                    true
                ]
            ]
        },
        {
            "index_i": 3,
            "index_j": 4,
            "use_case": "Tuerschliessbuegel",
            "sub_dir": "OK",
            "file": "WBA11AP02RCR47918_SdM0aIwBsfk0sxt0k6y_",
            "pics_label": true,
            "ai_advice": false,
            "is_ok_user": true,
            "marks_user": [],
            "timestamps": [
                [
                    1716362507107,
                    true
                ]
            ]
        },
        {
            "index_i": 3,
            "index_j": 5,
            "use_case": "Head-Airbag-Twist",
            "sub_dir": "NOK",
            "file": "WBY73AW07NFN14854_OvtaRIEBX6rLWZlyZfLL",
            "pics_label": false,
            "ai_advice": false,
            "is_ok_user": false,
            "marks_user": [],
            "timestamps": [
                [
                    1716362513709,
                    false
                ]
            ]
        },
        {
            "index_i": 4,
            "index_j": 0,
            "use_case": "Frontend-Luftklappe",
            "sub_dir": "NOK",
            "file": "WBA21BP01RCR96845_RVTQxo0BMQo0ENBQgeD-",
            "pics_label": false,
            "ai_advice": true,
            "is_ok_user": true,
            "marks_user": [],
            "timestamps": [
                [
                    1716362524013,
                    true
                ]
            ]
        },
        {
            "index_i": 4,
            "index_j": 1,
            "use_case": "Tuerschliessbuegel",
            "sub_dir": "NOK",
            "file": "WBA21GV090CP73875_bOMwtYsBWicZSVJ7k3aq",
            "pics_label": false,
            "ai_advice": false,
            "is_ok_user": false,
            "marks_user": [],
            "timestamps": [
                [
                    1716362525829,
                    false
                ]
            ]
        },
        {
            "index_i": 4,
            "index_j": 2,
            "use_case": "Head-Airbag-Twist",
            "sub_dir": "NOK",
            "file": "WBY83FB05RFS80498_RSrToo0Bsfk0sxt01WIQ",
            "pics_label": false,
            "ai_advice": true,
            "is_ok_user": true,
            "marks_user": [],
            "timestamps": [
                [
                    1716362527084,
                    true
                ]
            ]
        },
        {
            "index_i": 4,
            "index_j": 3,
            "use_case": "Gurt-Cabrio",
            "sub_dir": "NOK",
            "file": "WBADZ2C04RCN79047_Hb-wvogBphvdDuvqLUbe",
            "pics_label": false,
            "ai_advice": false,
            "is_ok_user": true,
            "marks_user": [],
            "timestamps": [
                [
                    1716362531640,
                    true
                ]
            ]
        },
        {
            "index_i": 4,
            "index_j": 4,
            "use_case": "Massekabel",
            "sub_dir": "OK",
            "file": "WBA11AJ060CR93229_h0z2sY0BMQo0ENBQnKHL",
            "pics_label": true,
            "ai_advice": true,
            "is_ok_user": true,
            "marks_user": [],
            "timestamps": [
                [
                    1716362530637,
                    true
                ]
            ]
        },
        {
            "index_i": 4,
            "index_j": 5,
            "use_case": "Wasserablaufschlauch",
            "sub_dir": "OK",
            "file": "WBA43FJ02RCR93911_EXyPsY0BWicZSVJ7azoi",
            "pics_label": true,
            "ai_advice": true,
            "is_ok_user": true,
            "marks_user": [],
            "timestamps": [
                [
                    1716362529636,
                    true
                ]
            ]
        },
        {
            "index_i": 5,
            "index_j": 0,
            "use_case": "Massekabel",
            "sub_dir": "NOK",
            "file": "WBA71AG00PCN38484_-asmtIcBishiNuVdncj8",
            "pics_label": false,
            "ai_advice": true,
            "is_ok_user": true,
            "marks_user": [],
            "timestamps": [
                [
                    1716362546781,
                    true
                ]
            ]
        },
        {
            "index_i": 5,
            "index_j": 1,
            "use_case": "Gurt-Cabrio",
            "sub_dir": "OK",
            "file": "WBADZ2C05RCR94720_pE8jwI0BMQo0ENBQuqzh",
            "pics_label": true,
            "ai_advice": true,
            "is_ok_user": true,
            "marks_user": [],
            "timestamps": [
                [
                    1716362548388,
                    true
                ]
            ]
        },
        {
            "index_i": 5,
            "index_j": 2,
            "use_case": "Tuerschliessbuegel",
            "sub_dir": "NOK",
            "file": "WBA11GV0X0CP73833_7pw-hosBPpjQesYB29jD",
            "pics_label": false,
            "ai_advice": false,
            "is_ok_user": false,
            "marks_user": [],
            "timestamps": [
                [
                    1716362550802,
                    false
                ]
            ]
        },
        {
            "index_i": 5,
            "index_j": 3,
            "use_case": "Frontend-Luftklappe",
            "sub_dir": "NOK",
            "file": "WBA21BP03RCR69551_nwR-VI0Bsfk0sxt01j9w",
            "pics_label": false,
            "ai_advice": false,
            "is_ok_user": true,
            "marks_user": [],
            "timestamps": [
                [
                    1716362555224,
                    true
                ]
            ]
        },
        {
            "index_i": 5,
            "index_j": 4,
            "use_case": "Head-Airbag-Twist",
            "sub_dir": "NOK",
            "file": "WBY41AW020FT07905_x9SDVo4BWicZSVJ7Qcsf",
            "pics_label": false,
            "ai_advice": false,
            "is_ok_user": true,
            "marks_user": [],
            "timestamps": [
                [
                    1716362554091,
                    true
                ]
            ]
        },
        {
            "index_i": 5,
            "index_j": 5,
            "use_case": "Wasserablaufschlauch",
            "sub_dir": "OK",
            "file": "WBA43FJ09RCR93825_xDQYsY0Bsfk0sxt0PZgP",
            "pics_label": true,
            "ai_advice": false,
            "is_ok_user": true,
            "marks_user": [],
            "timestamps": [
                [
                    1716362551991,
                    true
                ]
            ]
        },
        {
            "index_i": 6,
            "index_j": 0,
            "use_case": "Head-Airbag-Twist",
            "sub_dir": "NOK",
            "file": "WBY33AW03RFT06877_xNBkUY4BWicZSVJ7DcX7",
            "pics_label": false,
            "ai_advice": false,
            "is_ok_user": false,
            "marks_user": [],
            "timestamps": [
                [
                    1716362564053,
                    false
                ]
            ]
        },
        {
            "index_i": 6,
            "index_j": 1,
            "use_case": "Gurt-Cabrio",
            "sub_dir": "NOK",
            "file": "WBSDZ0C01RCR23160_svTD8YsBWicZSVJ762TH",
            "pics_label": false,
            "ai_advice": false,
            "is_ok_user": true,
            "marks_user": [],
            "timestamps": [
                [
                    1716362562119,
                    false
                ],
                [
                    1716362566293,
                    true
                ]
            ]
        },
        {
            "index_i": 6,
            "index_j": 2,
            "use_case": "Frontend-Luftklappe",
            "sub_dir": "NOK",
            "file": "WBA11BM060CP98409_dFHra4sBBFG6eYqgR5Ad",
            "pics_label": false,
            "ai_advice": false,
            "is_ok_user": true,
            "marks_user": [],
            "timestamps": [
                [
                    1716362567735,
                    true
                ]
            ]
        },
        {
            "index_i": 6,
            "index_j": 3,
            "use_case": "Tuerschliessbuegel",
            "sub_dir": "OK",
            "file": "WBA11AP02RCR43173_Esz7V4wBsfk0sxt06UPK",
            "pics_label": true,
            "ai_advice": true,
            "is_ok_user": true,
            "marks_user": [],
            "timestamps": [
                [
                    1716362571558,
                    true
                ]
            ]
        },
        {
            "index_i": 6,
            "index_j": 4,
            "use_case": "Wasserablaufschlauch",
            "sub_dir": "NOK",
            "file": "WBA43FJ02RCR71956_wwdvWY0Bsfk0sxt0eV4j",
            "pics_label": false,
            "ai_advice": false,
            "is_ok_user": false,
            "marks_user": [],
            "timestamps": [
                [
                    1716362570552,
                    false
                ]
            ]
        },
        {
            "index_i": 6,
            "index_j": 5,
            "use_case": "Massekabel",
            "sub_dir": "NOK",
            "file": "WBA11AJ080CN38429_Equds4cBishiNuVdLaKH",
            "pics_label": false,
            "ai_advice": false,
            "is_ok_user": true,
            "marks_user": [],
            "timestamps": [
                [
                    1716362569485,
                    true
                ]
            ]
        },
        {
            "index_i": 7,
            "index_j": 0,
            "use_case": "Tuerschliessbuegel",
            "sub_dir": "NOK",
            "file": "WBA11GV070CP43785_qg3KFIsBctDhixjaCWeN",
            "pics_label": false,
            "ai_advice": false,
            "is_ok_user": false,
            "marks_user": [],
            "timestamps": [
                [
                    1716362583133,
                    false
                ]
            ]
        },
        {
            "index_i": 7,
            "index_j": 1,
            "use_case": "Wasserablaufschlauch",
            "sub_dir": "NOK",
            "file": "WBY33FK04RCR71727_hwXGVo0Bsfk0sxt0i-rt",
            "pics_label": false,
            "ai_advice": true,
            "is_ok_user": true,
            "marks_user": [],
            "timestamps": [
                [
                    1716362577845,
                    true
                ]
            ]
        },
        {
            "index_i": 7,
            "index_j": 2,
            "use_case": "Gurt-Cabrio",
            "sub_dir": "OK",
            "file": "WBADZ2C00RCR68977_Xkd0RI0BWicZSVJ7_IbB",
            "pics_label": true,
            "ai_advice": false,
            "is_ok_user": true,
            "marks_user": [],
            "timestamps": [
                [
                    1716362578788,
                    true
                ]
            ]
        },
        {
            "index_i": 7,
            "index_j": 3,
            "use_case": "Massekabel",
            "sub_dir": "OK",
            "file": "WBA21BP00RCR95606_XlPaxI0BMQo0ENBQ2xiT",
            "pics_label": true,
            "ai_advice": true,
            "is_ok_user": false,
            "marks_user": [],
            "timestamps": [
                [
                    1716362581990,
                    false
                ]
            ]
        },
        {
            "index_i": 7,
            "index_j": 4,
            "use_case": "Frontend-Luftklappe",
            "sub_dir": "OK",
            "file": "WBA61CC03RCR95564_Mjrcwo0Bsfk0sxt0SsH1",
            "pics_label": true,
            "ai_advice": true,
            "is_ok_user": false,
            "marks_user": [],
            "timestamps": [
                [
                    1716362580909,
                    false
                ]
            ]
        },
        {
            "index_i": 7,
            "index_j": 5,
            "use_case": "Head-Airbag-Twist",
            "sub_dir": "OK",
            "file": "WBY43AW04RFT31100_SCl1B48BWicZSVJ7Z7iZ",
            "pics_label": true,
            "ai_advice": true,
            "is_ok_user": true,
            "marks_user": [],
            "timestamps": [
                [
                    1716362579789,
                    true
                ]
            ]
        },
        {
            "index_i": 8,
            "index_j": 0,
            "use_case": "Massekabel",
            "sub_dir": "NOK",
            "file": "WBA21BP04PCN38424_eT-Ss4cBgCrs9nhAyp6-",
            "pics_label": false,
            "ai_advice": false,
            "is_ok_user": true,
            "marks_user": [],
            "timestamps": [
                [
                    1716362590132,
                    true
                ]
            ]
        },
        {
            "index_i": 8,
            "index_j": 1,
            "use_case": "Gurt-Cabrio",
            "sub_dir": "NOK",
            "file": "WBADZ4C09RCP54744_2-XAaIoBctDhixjar1QE",
            "pics_label": false,
            "ai_advice": true,
            "is_ok_user": true,
            "marks_user": [],
            "timestamps": [
                [
                    1716362589110,
                    true
                ]
            ]
        },
        {
            "index_i": 8,
            "index_j": 2,
            "use_case": "Head-Airbag-Twist",
            "sub_dir": "OK",
            "file": "WBA11AV00RFS87850_0ItL0I0BWicZSVJ7obuC",
            "pics_label": true,
            "ai_advice": true,
            "is_ok_user": true,
            "marks_user": [],
            "timestamps": [
                [
                    1716362594372,
                    true
                ]
            ]
        },
        {
            "index_i": 8,
            "index_j": 3,
            "use_case": "Tuerschliessbuegel",
            "sub_dir": "OK",
            "file": "WBA11AP02RCR43156_0OOMV4wBMQo0ENBQYFHv",
            "pics_label": true,
            "ai_advice": false,
            "is_ok_user": true,
            "marks_user": [],
            "timestamps": [
                [
                    1716362590926,
                    true
                ]
            ]
        },
        {
            "index_i": 8,
            "index_j": 4,
            "use_case": "Wasserablaufschlauch",
            "sub_dir": "OK",
            "file": "WBA43FJ08RCR94206_NDb8so0Bsfk0sxt0cjW5",
            "pics_label": true,
            "ai_advice": true,
            "is_ok_user": false,
            "marks_user": [],
            "timestamps": [
                [
                    1716362592374,
                    false
                ]
            ]
        },
        {
            "index_i": 8,
            "index_j": 5,
            "use_case": "Frontend-Luftklappe",
            "sub_dir": "OK",
            "file": "WBA11AJ090CR92396_5kmRrY0BMQo0ENBQCHP8",
            "pics_label": true,
            "ai_advice": true,
            "is_ok_user": true,
            "marks_user": [],
            "timestamps": [
                [
                    1716362593575,
                    true
                ]
            ]
        },
        {
            "index_i": 9,
            "index_j": 0,
            "use_case": "Head-Airbag-Twist",
            "sub_dir": "OK",
            "file": "WBY71AW0XRFT30827_6ChgBo8BWicZSVJ7u8OE",
            "pics_label": true,
            "ai_advice": true,
            "is_ok_user": false,
            "marks_user": [],
            "timestamps": [
                [
                    1716362607812,
                    false
                ]
            ]
        },
        {
            "index_i": 9,
            "index_j": 1,
            "use_case": "Frontend-Luftklappe",
            "sub_dir": "NOK",
            "file": "WBA21BP02RCR69525_QgMCVI0Bsfk0sxt0fuJe",
            "pics_label": false,
            "ai_advice": true,
            "is_ok_user": true,
            "marks_user": [],
            "timestamps": [
                [
                    1716362600089,
                    true
                ]
            ]
        },
        {
            "index_i": 9,
            "index_j": 2,
            "use_case": "Wasserablaufschlauch",
            "sub_dir": "OK",
            "file": "WBA43FJ09RCR93176__EuosI0BMQo0ENBQ_IRE",
            "pics_label": true,
            "ai_advice": true,
            "is_ok_user": true,
            "marks_user": [],
            "timestamps": [
                [
                    1716362601421,
                    true
                ]
            ]
        },
        {
            "index_i": 9,
            "index_j": 3,
            "use_case": "Tuerschliessbuegel",
            "sub_dir": "NOK",
            "file": "WBA11GV010CP43765_BCSw_4oBmbs2iq29ZZBI - Kopie",
            "pics_label": false,
            "ai_advice": true,
            "is_ok_user": false,
            "marks_user": [],
            "timestamps": [
                [
                    1716362606652,
                    false
                ]
            ]
        },
        {
            "index_i": 9,
            "index_j": 4,
            "use_case": "Gurt-Cabrio",
            "sub_dir": "NOK",
            "file": "WBSDZ0C01RCR19996_3Kju24sBsfk0sxt06zce",
            "pics_label": false,
            "ai_advice": false,
            "is_ok_user": true,
            "marks_user": [],
            "timestamps": [
                [
                    1716362604940,
                    true
                ]
            ]
        },
        {
            "index_i": 9,
            "index_j": 5,
            "use_case": "Massekabel",
            "sub_dir": "NOK",
            "file": "WBA51BL0X0CN38422_cz-Ns4cBgCrs9nhAL5xP",
            "pics_label": false,
            "ai_advice": false,
            "is_ok_user": true,
            "marks_user": [],
            "timestamps": [
                [
                    1716362603260,
                    true
                ]
            ]
        },
        {
            "index_i": 10,
            "index_j": 0,
            "use_case": "Massekabel",
            "sub_dir": "NOK",
            "file": "WBA71AG0XPCN38492_XD81tIcBgCrs9nhATc1m",
            "pics_label": false,
            "ai_advice": true,
            "is_ok_user": false,
            "marks_user": [],
            "timestamps": [
                [
                    1716362616134,
                    false
                ]
            ]
        },
        {
            "index_i": 10,
            "index_j": 1,
            "use_case": "Gurt-Cabrio",
            "sub_dir": "OK",
            "file": "WBSDZ01080CR54945_SypD_IwBWicZSVJ7n5uz",
            "pics_label": true,
            "ai_advice": false,
            "is_ok_user": true,
            "marks_user": [],
            "timestamps": [
                [
                    1716362617118,
                    true
                ]
            ]
        },
        {
            "index_i": 10,
            "index_j": 2,
            "use_case": "Wasserablaufschlauch",
            "sub_dir": "NOK",
            "file": "WBA43FJ05RCR85091_DzkPjI0BMQo0ENBQ_Obe",
            "pics_label": false,
            "ai_advice": false,
            "is_ok_user": false,
            "marks_user": [],
            "timestamps": [
                [
                    1716362618173,
                    false
                ]
            ]
        },
        {
            "index_i": 10,
            "index_j": 3,
            "use_case": "Frontend-Luftklappe",
            "sub_dir": "OK",
            "file": "WBA21BP00RCR93547_0jaOs40Bsfk0sxt08rO1",
            "pics_label": true,
            "ai_advice": true,
            "is_ok_user": true,
            "marks_user": [],
            "timestamps": [
                [
                    1716362626990,
                    true
                ]
            ]
        },
        {
            "index_i": 10,
            "index_j": 4,
            "use_case": "Head-Airbag-Twist",
            "sub_dir": "NOK",
            "file": "WBY43AW07RFT08894_-JF9W44Bsfk0sxt0mWeM",
            "pics_label": false,
            "ai_advice": false,
            "is_ok_user": true,
            "marks_user": [],
            "timestamps": [
                [
                    1716362620751,
                    true
                ]
            ]
        },
        {
            "index_i": 10,
            "index_j": 5,
            "use_case": "Tuerschliessbuegel",
            "sub_dir": "NOK",
            "file": "WBA11GW0X0CN83481_nLH3QIkBctDhixjavTY_",
            "pics_label": false,
            "ai_advice": false,
            "is_ok_user": true,
            "marks_user": [],
            "timestamps": [
                [
                    1716362619552,
                    true
                ]
            ]
        },
        {
            "index_i": 11,
            "index_j": 0,
            "use_case": "Frontend-Luftklappe",
            "sub_dir": "OK",
            "file": "WBA11CG010CR92492_t0vxsI0BMQo0ENBQccNb",
            "pics_label": true,
            "ai_advice": false,
            "is_ok_user": false,
            "marks_user": [],
            "timestamps": [
                [
                    1716362632446,
                    false
                ]
            ]
        },
        {
            "index_i": 11,
            "index_j": 1,
            "use_case": "Gurt-Cabrio",
            "sub_dir": "OK",
            "file": "WBADZ2C01RCR29945_0wDHFYwBWicZSVJ7eiL_",
            "pics_label": true,
            "ai_advice": false,
            "is_ok_user": true,
            "marks_user": [],
            "timestamps": [
                [
                    1716362633536,
                    true
                ]
            ]
        },
        {
            "index_i": 11,
            "index_j": 2,
            "use_case": "Head-Airbag-Twist",
            "sub_dir": "NOK",
            "file": "WBY71AW04RFT08886_0qh2W44BMQo0ENBQQr72",
            "pics_label": false,
            "ai_advice": false,
            "is_ok_user": false,
            "marks_user": [],
            "timestamps": [
                [
                    1716362634206,
                    false
                ]
            ]
        },
        {
            "index_i": 11,
            "index_j": 3,
            "use_case": "Massekabel",
            "sub_dir": "OK",
            "file": "WBA21BP00RCR95623_toNwxY0BWicZSVJ7v5h5",
            "pics_label": true,
            "ai_advice": true,
            "is_ok_user": true,
            "marks_user": [],
            "timestamps": [
                [
                    1716362637144,
                    true
                ]
            ]
        },
        {
            "index_i": 11,
            "index_j": 4,
            "use_case": "Wasserablaufschlauch",
            "sub_dir": "NOK",
            "file": "WBA43FJ06RCR83298_FjSYhI0BMQo0ENBQZ_EK",
            "pics_label": false,
            "ai_advice": false,
            "is_ok_user": true,
            "marks_user": [],
            "timestamps": [
                [
                    1716362636347,
                    true
                ]
            ]
        },
        {
            "index_i": 11,
            "index_j": 5,
            "use_case": "Tuerschliessbuegel",
            "sub_dir": "OK",
            "file": "WBA11AP03RCR46163_iRYjXowBWicZSVJ7qlRm",
            "pics_label": true,
            "ai_advice": true,
            "is_ok_user": true,
            "marks_user": [],
            "timestamps": [
                [
                    1716362635357,
                    true
                ]
            ]
        },
        {
            "index_i": 12,
            "index_j": 0,
            "use_case": "Frontend-Luftklappe",
            "sub_dir": "NOK",
            "file": "WBA21BP09RCR66007_AhDlN40BMQo0ENBQs6G7",
            "pics_label": false,
            "ai_advice": false,
            "is_ok_user": false,
            "marks_user": [],
            "timestamps": [
                [
                    1716362643083,
                    false
                ]
            ]
        },
        {
            "index_i": 12,
            "index_j": 1,
            "use_case": "Gurt-Cabrio",
            "sub_dir": "OK",
            "file": "WBADZ2C05RCR16146_frfpyIsBMQo0ENBQwvAq",
            "pics_label": true,
            "ai_advice": true,
            "is_ok_user": true,
            "marks_user": [],
            "timestamps": [
                [
                    1716362644169,
                    true
                ]
            ]
        },
        {
            "index_i": 12,
            "index_j": 2,
            "use_case": "Tuerschliessbuegel",
            "sub_dir": "NOK",
            "file": "WBA21GV030CP43867_-lV-SYsBUwXShj1FqPDJ",
            "pics_label": false,
            "ai_advice": false,
            "is_ok_user": true,
            "marks_user": [],
            "timestamps": [
                [
                    1716362644730,
                    true
                ]
            ]
        },
        {
            "index_i": 12,
            "index_j": 3,
            "use_case": "Wasserablaufschlauch",
            "sub_dir": "NOK",
            "file": "WBY33FK07RCR92703_7Ui0rI0BMQo0ENBQQp-k",
            "pics_label": false,
            "ai_advice": true,
            "is_ok_user": true,
            "marks_user": [],
            "timestamps": [
                [
                    1716362648349,
                    true
                ]
            ]
        },
        {
            "index_i": 12,
            "index_j": 4,
            "use_case": "Massekabel",
            "sub_dir": "OK",
            "file": "WBA21BP0XRCR89070_FCsvpI0Bsfk0sxt0J1Vr",
            "pics_label": true,
            "ai_advice": false,
            "is_ok_user": true,
            "marks_user": [],
            "timestamps": [
                [
                    1716362647094,
                    true
                ]
            ]
        },
        {
            "index_i": 12,
            "index_j": 5,
            "use_case": "Head-Airbag-Twist",
            "sub_dir": "NOK",
            "file": "WBA11AV01NFM97559_kPS_qoABX6rLWZlyG609",
            "pics_label": false,
            "ai_advice": false,
            "is_ok_user": false,
            "marks_user": [],
            "timestamps": [
                [
                    1716362645805,
                    false
                ]
            ]
        },
        {
            "index_i": 13,
            "index_j": 0,
            "use_case": "Head-Airbag-Twist",
            "sub_dir": "NOK",
            "file": "WBY71AW0X0FR43498_QeZg6YgBpUCXOdhPCQle",
            "pics_label": false,
            "ai_advice": false,
            "is_ok_user": false,
            "marks_user": [],
            "timestamps": [
                [
                    1716362665599,
                    false
                ]
            ]
        },
        {
            "index_i": 13,
            "index_j": 1,
            "use_case": "Gurt-Cabrio",
            "sub_dir": "NOK",
            "file": "WBAFY4C06RCR40592_4Mg7RYwBsfk0sxt0MZBt",
            "pics_label": false,
            "ai_advice": false,
            "is_ok_user": true,
            "marks_user": [],
            "timestamps": [
                [
                    1716362656637,
                    true
                ]
            ]
        },
        {
            "index_i": 13,
            "index_j": 2,
            "use_case": "Wasserablaufschlauch",
            "sub_dir": "OK",
            "file": "WBA43FJ09RCR94361_c06ys40BMQo0ENBQLx1q",
            "pics_label": true,
            "ai_advice": true,
            "is_ok_user": true,
            "marks_user": [],
            "timestamps": [
                [
                    1716362657725,
                    true
                ]
            ]
        },
        {
            "index_i": 13,
            "index_j": 3,
            "use_case": "Tuerschliessbuegel",
            "sub_dir": "OK",
            "file": "WBA11AP00RCR47612_DuruZowBMQo0ENBQ7kuF",
            "pics_label": true,
            "ai_advice": true,
            "is_ok_user": false,
            "marks_user": [],
            "timestamps": [
                [
                    1716362664413,
                    false
                ]
            ]
        },
        {
            "index_i": 13,
            "index_j": 4,
            "use_case": "Massekabel",
            "sub_dir": "NOK",
            "file": "WBAJY8100RCP25164_j_uekYkBUwXShj1FK45M",
            "pics_label": false,
            "ai_advice": false,
            "is_ok_user": true,
            "marks_user": [],
            "timestamps": [
                [
                    1716362659468,
                    true
                ]
            ]
        },
        {
            "index_i": 13,
            "index_j": 5,
            "use_case": "Frontend-Luftklappe",
            "sub_dir": "OK",
            "file": "WBA21BP00RCR93550_1n6gs40BWicZSVJ7FAKm",
            "pics_label": true,
            "ai_advice": false,
            "is_ok_user": false,
            "marks_user": [],
            "timestamps": [
                [
                    1716362658677,
                    false
                ]
            ]
        },
        {
            "index_i": 14,
            "index_j": 0,
            "use_case": "Wasserablaufschlauch",
            "sub_dir": "OK",
            "file": "WBA43FJ08RCR95744_olDgwI0BMQo0ENBQTkuh",
            "pics_label": true,
            "ai_advice": true,
            "is_ok_user": true,
            "marks_user": [],
            "timestamps": [
                [
                    1716362672777,
                    true
                ]
            ]
        },
        {
            "index_i": 14,
            "index_j": 1,
            "use_case": "Frontend-Luftklappe",
            "sub_dir": "OK",
            "file": "WBA21BP00RCR92527_d3zAsY0BWicZSVJ74GC6",
            "pics_label": true,
            "ai_advice": true,
            "is_ok_user": false,
            "marks_user": [],
            "timestamps": [
                [
                    1716362674041,
                    false
                ]
            ]
        },
        {
            "index_i": 14,
            "index_j": 2,
            "use_case": "Massekabel",
            "sub_dir": "NOK",
            "file": "WBA13BK00PCN35887_Cz0LoIcBgCrs9nhA4nDE",
            "pics_label": false,
            "ai_advice": true,
            "is_ok_user": true,
            "marks_user": [],
            "timestamps": [
                [
                    1716362675442,
                    true
                ]
            ]
        },
        {
            "index_i": 14,
            "index_j": 3,
            "use_case": "Gurt-Cabrio",
            "sub_dir": "NOK",
            "file": "WBADZ21010CR79153_zRQueI0Bsfk0sxt07vnL",
            "pics_label": false,
            "ai_advice": false,
            "is_ok_user": true,
            "marks_user": [],
            "timestamps": [
                [
                    1716362683479,
                    true
                ]
            ]
        },
        {
            "index_i": 14,
            "index_j": 4,
            "use_case": "Tuerschliessbuegel",
            "sub_dir": "OK",
            "file": "WBA11AP03RCR44719_sBWPXIwBWicZSVJ74Xr6",
            "pics_label": true,
            "ai_advice": true,
            "is_ok_user": true,
            "marks_user": [],
            "timestamps": [
                [
                    1716362678240,
                    true
                ]
            ]
        },
        {
            "index_i": 14,
            "index_j": 5,
            "use_case": "Head-Airbag-Twist",
            "sub_dir": "OK",
            "file": "WBY83FB08RFT30598_hieQBY8BWicZSVJ7HPDl",
            "pics_label": true,
            "ai_advice": true,
            "is_ok_user": false,
            "marks_user": [],
            "timestamps": [
                [
                    1716362676552,
                    true
                ],
                [
                    1716362677131,
                    false
                ]
            ]
        },
        {
            "index_i": 15,
            "index_j": 0,
            "use_case": "Frontend-Luftklappe",
            "sub_dir": "OK",
            "file": "WBA21BP0XRCR93524_BX2kso0BWicZSVJ78jUS",
            "pics_label": true,
            "ai_advice": true,
            "is_ok_user": false,
            "marks_user": [],
            "timestamps": [
                [
                    1716362688955,
                    false
                ]
            ]
        },
        {
            "index_i": 15,
            "index_j": 1,
            "use_case": "Tuerschliessbuegel",
            "sub_dir": "OK",
            "file": "WBA11AP0XRCR43194_iRO0WIwBWicZSVJ7jciI",
            "pics_label": true,
            "ai_advice": true,
            "is_ok_user": true,
            "marks_user": [],
            "timestamps": [
                [
                    1716362690033,
                    true
                ]
            ]
        },
        {
            "index_i": 15,
            "index_j": 2,
            "use_case": "Head-Airbag-Twist",
            "sub_dir": "OK",
            "file": "WBA11AV08RFS87367_EllDzY0BMQo0ENBQheLZ",
            "pics_label": true,
            "ai_advice": true,
            "is_ok_user": true,
            "marks_user": [],
            "timestamps": [
                [
                    1716362691629,
                    true
                ]
            ]
        },
        {
            "index_i": 15,
            "index_j": 3,
            "use_case": "Gurt-Cabrio",
            "sub_dir": "NOK",
            "file": "WBADZ22000CR65923_nRC0N40BMQo0ENBQQIAA",
            "pics_label": false,
            "ai_advice": false,
            "is_ok_user": true,
            "marks_user": [],
            "timestamps": [
                [
                    1716362694429,
                    true
                ]
            ]
        },
        {
            "index_i": 15,
            "index_j": 4,
            "use_case": "Wasserablaufschlauch",
            "sub_dir": "OK",
            "file": "WBA43FJ02RCR95822_8Dk3wY0Bsfk0sxt0zk2R",
            "pics_label": true,
            "ai_advice": true,
            "is_ok_user": true,
            "marks_user": [],
            "timestamps": [
                [
                    1716362693551,
                    true
                ]
            ]
        },
        {
            "index_i": 15,
            "index_j": 5,
            "use_case": "Massekabel",
            "sub_dir": "NOK",
            "file": "WBA31AJ070CP25170_VcStkYkBctDhixjaRY6i",
            "pics_label": false,
            "ai_advice": true,
            "is_ok_user": true,
            "marks_user": [],
            "timestamps": [
                [
                    1716362692617,
                    true
                ]
            ]
        },
        {
            "index_i": 16,
            "index_j": 0,
            "use_case": "Frontend-Luftklappe",
            "sub_dir": "OK",
            "file": "WBA11AJ0X0CR92424_BDImro0Bsfk0sxt04qnb",
            "pics_label": true,
            "ai_advice": true,
            "is_ok_user": false,
            "marks_user": [],
            "timestamps": [
                [
                    1716362700221,
                    false
                ]
            ]
        },
        {
            "index_i": 16,
            "index_j": 1,
            "use_case": "Gurt-Cabrio",
            "sub_dir": "OK",
            "file": "WBADZ2C03RCR92108_GXs3sI0BWicZSVJ7KQ1A",
            "pics_label": true,
            "ai_advice": false,
            "is_ok_user": true,
            "marks_user": [],
            "timestamps": [
                [
                    1716362709103,
                    true
                ]
            ]
        },
        {
            "index_i": 16,
            "index_j": 2,
            "use_case": "Wasserablaufschlauch",
            "sub_dir": "NOK",
            "file": "WBY43FK0XRCR84874_tiFliY0Bsfk0sxt0pS4u",
            "pics_label": false,
            "ai_advice": false,
            "is_ok_user": false,
            "marks_user": [],
            "timestamps": [
                [
                    1716362702207,
                    false
                ]
            ]
        },
        {
            "index_i": 16,
            "index_j": 3,
            "use_case": "Tuerschliessbuegel",
            "sub_dir": "OK",
            "file": "WBA11AP03RCR44655_m-RTWYwBMQo0ENBQQklL",
            "pics_label": true,
            "ai_advice": true,
            "is_ok_user": true,
            "marks_user": [],
            "timestamps": [
                [
                    1716362705260,
                    true
                ]
            ]
        },
        {
            "index_i": 16,
            "index_j": 4,
            "use_case": "Massekabel",
            "sub_dir": "NOK",
            "file": "WBA61CC03PCN38427_IJKXs4cBLWg_BhSSfiLK",
            "pics_label": false,
            "ai_advice": false,
            "is_ok_user": true,
            "marks_user": [],
            "timestamps": [
                [
                    1716362703989,
                    true
                ]
            ]
        },
        {
            "index_i": 16,
            "index_j": 5,
            "use_case": "Head-Airbag-Twist",
            "sub_dir": "NOK",
            "file": "WBA63AW04RFT07273_m9LsUo4BWicZSVJ7oC-t",
            "pics_label": false,
            "ai_advice": true,
            "is_ok_user": false,
            "marks_user": [],
            "timestamps": [
                [
                    1716362703115,
                    false
                ]
            ]
        },
        {
            "index_i": 17,
            "index_j": 0,
            "use_case": "Head-Airbag-Twist",
            "sub_dir": "OK",
            "file": "WBA11AV06RFS87951_tUTD0I0Bsfk0sxt0G9qY",
            "pics_label": true,
            "ai_advice": true,
            "is_ok_user": false,
            "marks_user": [],
            "timestamps": [
                [
                    1716362726342,
                    false
                ]
            ]
        },
        {
            "index_i": 17,
            "index_j": 1,
            "use_case": "Frontend-Luftklappe",
            "sub_dir": "NOK",
            "file": "WBA21BP02RCR76295_QVkUao0BWicZSVJ7kXgI",
            "pics_label": false,
            "ai_advice": false,
            "is_ok_user": false,
            "marks_user": [],
            "timestamps": [
                [
                    1716362715644,
                    true
                ],
                [
                    1716362717713,
                    false
                ]
            ]
        },
        {
            "index_i": 17,
            "index_j": 2,
            "use_case": "Gurt-Cabrio",
            "sub_dir": "NOK",
            "file": "WBADZ2C09RCR08857_yJUYpYsBsfk0sxt0FCIG",
            "pics_label": false,
            "ai_advice": false,
            "is_ok_user": true,
            "marks_user": [],
            "timestamps": [
                [
                    1716362716796,
                    true
                ]
            ]
        },
        {
            "index_i": 17,
            "index_j": 3,
            "use_case": "Tuerschliessbuegel",
            "sub_dir": "NOK",
            "file": "WBA21GW000CP43839_SBseP4sBctDhixjagj7m",
            "pics_label": false,
            "ai_advice": false,
            "is_ok_user": true,
            "marks_user": [],
            "timestamps": [
                [
                    1716362719084,
                    true
                ],
                [
                    1716362719499,
                    true
                ]
            ]
        },
        {
            "index_i": 17,
            "index_j": 4,
            "use_case": "Massekabel",
            "sub_dir": "OK",
            "file": "WBA11BM03RCR89086_4SzzpY0Bsfk0sxt0Tx2b",
            "pics_label": true,
            "ai_advice": true,
            "is_ok_user": true,
            "marks_user": [],
            "timestamps": [
                [
                    1716362720454,
                    true
                ]
            ]
        },
        {
            "index_i": 17,
            "index_j": 5,
            "use_case": "Wasserablaufschlauch",
            "sub_dir": "OK",
            "file": "WBA43FJ02RCR93911_czSPsY0Bsfk0sxt0zfrg",
            "pics_label": true,
            "ai_advice": true,
            "is_ok_user": true,
            "marks_user": [],
            "timestamps": [
                [
                    1716362721852,
                    false
                ],
                [
                    1716362722646,
                    true
                ]
            ]
        },
        {
            "index_i": 18,
            "index_j": 0,
            "use_case": "Wasserablaufschlauch",
            "sub_dir": "NOK",
            "file": "WBA53FJ04RCR74877_SwwnYY0Bsfk0sxt0VpCT",
            "pics_label": false,
            "ai_advice": false,
            "is_ok_user": true,
            "marks_user": [],
            "timestamps": [
                [
                    1716362732405,
                    true
                ]
            ]
        },
        {
            "index_i": 18,
            "index_j": 1,
            "use_case": "Massekabel",
            "sub_dir": "OK",
            "file": "WBA11AJ040CR89096_FiwYpo0Bsfk0sxt0UEKJ",
            "pics_label": true,
            "ai_advice": true,
            "is_ok_user": true,
            "marks_user": [],
            "timestamps": [
                [
                    1716362733743,
                    true
                ]
            ]
        },
        {
            "index_i": 18,
            "index_j": 2,
            "use_case": "Frontend-Luftklappe",
            "sub_dir": "NOK",
            "file": "WBA21BP00RCR50830_b-8OfowBMQo0ENBQRKT1",
            "pics_label": false,
            "ai_advice": false,
            "is_ok_user": false,
            "marks_user": [],
            "timestamps": [
                [
                    1716362734855,
                    false
                ]
            ]
        },
        {
            "index_i": 18,
            "index_j": 3,
            "use_case": "Gurt-Cabrio",
            "sub_dir": "OK",
            "file": "WBADZ2C08RCR40554_ed5UQIwBMQo0ENBQQAb9",
            "pics_label": true,
            "ai_advice": true,
            "is_ok_user": true,
            "marks_user": [],
            "timestamps": [
                [
                    1716362738630,
                    true
                ]
            ]
        },
        {
            "index_i": 18,
            "index_j": 4,
            "use_case": "Tuerschliessbuegel",
            "sub_dir": "NOK",
            "file": "WBA11GV040CP73858_E6_KqosBMQo0ENBQZgBt",
            "pics_label": false,
            "ai_advice": false,
            "is_ok_user": true,
            "marks_user": [],
            "timestamps": [
                [
                    1716362736875,
                    true
                ]
            ]
        },
        {
            "index_i": 18,
            "index_j": 5,
            "use_case": "Head-Airbag-Twist",
            "sub_dir": "OK",
            "file": "WBA11AV05RFS87021_YFjuy40BMQo0ENBQ-7b1",
            "pics_label": true,
            "ai_advice": false,
            "is_ok_user": false,
            "marks_user": [],
            "timestamps": [
                [
                    1716362735829,
                    false
                ]
            ]
        },
        {
            "index_i": 19,
            "index_j": 0,
            "use_case": "Frontend-Luftklappe",
            "sub_dir": "NOK",
            "file": "WBA21BP02RCR77785_2C2zeY0BMQo0ENBQyomI",
            "pics_label": false,
            "ai_advice": false,
            "is_ok_user": false,
            "marks_user": [],
            "timestamps": [
                [
                    1716362743877,
                    false
                ]
            ]
        },
        {
            "index_i": 19,
            "index_j": 1,
            "use_case": "Massekabel",
            "sub_dir": "OK",
            "file": "WBA11AJ080CR92406_hEjUrI0BMQo0ENBQib-K",
            "pics_label": true,
            "ai_advice": false,
            "is_ok_user": true,
            "marks_user": [],
            "timestamps": [
                [
                    1716362744704,
                    true
                ]
            ]
        },
        {
            "index_i": 19,
            "index_j": 2,
            "use_case": "Gurt-Cabrio",
            "sub_dir": "OK",
            "file": "WBADZ2C08RCR49125_M--qfYwBMQo0ENBQfYKw",
            "pics_label": true,
            "ai_advice": true,
            "is_ok_user": false,
            "marks_user": [],
            "timestamps": [
                [
                    1716362745389,
                    false
                ]
            ]
        },
        {
            "index_i": 19,
            "index_j": 3,
            "use_case": "Tuerschliessbuegel",
            "sub_dir": "NOK",
            "file": "WBA31GV010CP43841_NjZsPosBmbs2iq295VEE",
            "pics_label": false,
            "ai_advice": true,
            "is_ok_user": false,
            "marks_user": [],
            "timestamps": [
                [
                    1716362747974,
                    false
                ]
            ]
        },
        {
            "index_i": 19,
            "index_j": 4,
            "use_case": "Head-Airbag-Twist",
            "sub_dir": "OK",
            "file": "WBA11AV04RFS87043_R0EDzI0Bsfk0sxt0O3ut",
            "pics_label": true,
            "ai_advice": true,
            "is_ok_user": false,
            "marks_user": [],
            "timestamps": [
                [
                    1716362747115,
                    false
                ]
            ]
        },
        {
            "index_i": 19,
            "index_j": 5,
            "use_case": "Wasserablaufschlauch",
            "sub_dir": "NOK",
            "file": "WBY33FK03RCR83285_7zSKhI0BMQo0ENBQGeKy",
            "pics_label": false,
            "ai_advice": false,
            "is_ok_user": false,
            "marks_user": [],
            "timestamps": [
                [
                    1716362746396,
                    false
                ]
            ]
        }
    ]
}